jogger/__init__.py
jogger/exceptions.py
jogger/jog.py
jogger/tasks/__init__.py
jogger/tasks/_release.py
jogger/tasks/base.py
jogger/tasks/django.py
jogger/tasks/docs.py
jogger/tasks/lint.py
jogger/tasks/test.py
jogger/tasks/update.py
jogger/utils/__init__.py
jogger/utils/config.py
jogger/utils/files.py
jogger/utils/output.py
task_jogger-2.0.2.dist-info/LICENSE
task_jogger-2.0.2.dist-info/METADATA
task_jogger-2.0.2.dist-info/WHEEL
task_jogger-2.0.2.dist-info/entry_points.txt
task_jogger-2.0.2.dist-info/top_level.txt
task_jogger-2.0.2.dist-info/RECORD
