Metadata-Version: 2.1
Name: task-jogger
Version: 2.0.2
Summary: A simple Python-based command line tool that is not quite a fully-fledged task runner.
Author-email: Alex Church <alex@church.id.au>
License: MIT
Project-URL: Homepage, https://github.com/oogles/task-jogger
Project-URL: Documentation, https://task-jogger.readthedocs.io/en/latest/
Project-URL: Source, https://github.com/oogles/task-jogger
Project-URL: Tracker, https://github.com/oogles/task-jogger/issues
Classifier: Intended Audience :: Developers
Classifier: License :: OSI Approved :: MIT License
Classifier: Operating System :: OS Independent
Classifier: Programming Language :: Python
Classifier: Programming Language :: Python :: 3
Requires-Python: >=3.10
License-File: LICENSE
